pyluchtmeetnet/__init__.py
pyluchtmeetnet-0.1.3.dist-info/LICENSE
pyluchtmeetnet-0.1.3.dist-info/METADATA
pyluchtmeetnet-0.1.3.dist-info/WHEEL
pyluchtmeetnet-0.1.3.dist-info/top_level.txt
pyluchtmeetnet-0.1.3.dist-info/RECORD
