Metadata-Version: 2.1
Name: pyluchtmeetnet
Version: 0.1.3
Summary: A module for getting air quality data from Luchtmeetnet OpenAPI
Home-page: https://github.com/metbril/pyluchtmeetnet
Author: Robert van Bregt
Author-email: robertvanbregt@gmail.com
Project-URL: Bug Reports, https://github.com/metbril/pyluchtmeetnet/issues
Project-URL: Funding, https://ko-fi.com/metbril
Project-URL: Source, https://github.com/metbril/pyluchtmeetnet/
Keywords: air quality,health,api
Classifier: Development Status :: 4 - Beta
Classifier: Intended Audience :: Developers
Classifier: Topic :: Software Development :: Build Tools
Classifier: License :: OSI Approved :: MIT License
Classifier: Programming Language :: Python :: 3
Classifier: Programming Language :: Python :: 3.8
Classifier: Programming Language :: Python :: 3.9
Classifier: Programming Language :: Python :: 3.10
Classifier: Programming Language :: Python :: 3.11
Classifier: Programming Language :: Python :: 3.12
Classifier: Programming Language :: Python :: 3 :: Only
Requires-Python: >=3.8, <4
License-File: LICENSE
Requires-Dist: requests
